pyADiff/__init__.py
pyADiff/adjoint.py
pyADiff/differentiation.py
pyADiff/exceptions.py
pyADiff/math_functions.py
pyADiff/tangent.py
pyADiff/version.py
pyADiff-0.1.1.dist-info/LICENSE
pyADiff-0.1.1.dist-info/METADATA
pyADiff-0.1.1.dist-info/WHEEL
pyADiff-0.1.1.dist-info/top_level.txt
pyADiff-0.1.1.dist-info/RECORD
