Metadata-Version: 2.1
Name: pyADiff
Version: 0.1.1
Summary: A simple, pure python algorithmic differentiation package
Home-page: https://github.com/tam724/pyADiff
Author: Tamme Claus
Author-email: tamme.claus@gmail.com
License: GNU GPLv3 
Platform: UNKNOWN
Requires-Python: >=3.6
Requires-Dist: numpy (>=1.17)
